rhythmoscope/__init__.py
rhythmoscope/ems/__init__.py
rhythmoscope/ems/ems_base.py
rhythmoscope/ems/ems_extractor.py
rhythmoscope/envelope/__init__.py
rhythmoscope/envelope/base.py
rhythmoscope/envelope/envelope.py
rhythmoscope/envelope/momel.py
rhythmoscope/plot/__init__.py
rhythmoscope/signal/__init__.py
rhythmoscope/signal/filters.py
rhythmoscope/signal/pitch.py
rhythmoscope/signal/rolling_window.py
rhythmoscope/signal/utils.py
rhythmoscope/spectrogram/__init__.py
rhythmoscope/spectrogram/base.py
rhythmoscope/spectrogram/rhythm_spectrogram.py
rhythmoscope-0.1.1.dist-info/LICENSE
rhythmoscope-0.1.1.dist-info/METADATA
rhythmoscope-0.1.1.dist-info/WHEEL
rhythmoscope-0.1.1.dist-info/RECORD
