Metadata-Version: 2.1
Name: rhythmoscope
Version: 0.1.1
Summary: Implementation of the Envelope modulation spectrum for speech rhythm analysis
License: BSD-3-Clause
Author: Vaysse Robin
Author-email: robinvaysse@hotmail.fr
Requires-Python: >=3.9,<4.0
Classifier: License :: OSI Approved :: BSD License
Classifier: Programming Language :: Python :: 3
Classifier: Programming Language :: Python :: 3.9
Classifier: Programming Language :: Python :: 3.10
Classifier: Programming Language :: Python :: 3.11
Classifier: Programming Language :: Python :: 3.12
Requires-Dist: matplotlib (>=3.9.0,<4.0.0)
Requires-Dist: numpy (>=1.26.4,<2.0.0)
Requires-Dist: pandas (>=2.2.1,<3.0.0)
Requires-Dist: plotly (>=5.19.0,<6.0.0)
Requires-Dist: scipy (>=1.12.0,<2.0.0)
